trm/cline/__init__.py
trm.cline-1.0.0.dist-info/LICENSE.txt
trm.cline-1.0.0.dist-info/METADATA
trm.cline-1.0.0.dist-info/WHEEL
trm.cline-1.0.0.dist-info/top_level.txt
trm.cline-1.0.0.dist-info/RECORD
